{"title":"It's Always Sunny In Philadelphia","id":"tg_name_AlwaysSunny","net.maunium.telegram.pack":{"short_name":"AlwaysSunny","hash":"unimplemented"},"stickers":[{"body":"😈","url":"mxc://xethos.net/JzHTguoWZoHzIodwZgPYWkYG","info":{"w":512,"h":512,"size":38008,"mimetype":"image/webp","thumbnail_url":"mxc://xethos.net/JzHTguoWZoHzIodwZgPYWkYG","thumbnail_info":{"w":512,"h":512,"size":38008,"mimetype":"image/webp"}},"msgtype":"m.sticker","id":"tg_file_id_CAACAgEAAxUAAWT9uWjKS_pnlvG-5_Damxygy-wrAAISAAOIAg0IG1Y8d86uJK8wBA","net.maunium.telegram.sticker":{"pack":{"id":"unimplemented","short_name":"AlwaysSunny"},"id":"unimplemented","emoticons":["😈"]}},{"body":"🍑","url":"mxc://xethos.net/vBHReXdhQTeiHuOVcXdiefUb","info":{"w":512,"h":512,"size":19844,"mimetype":"image/webp","thumbnail_url":"mxc://xethos.net/vBHReXdhQTeiHuOVcXdiefUb","thumbnail_info":{"w":512,"h":512,"size":19844,"mimetype":"image/webp"}},"msgtype":"m.sticker","id":"tg_file_id_CAACAgEAAxUAAWT9uWjsqnlIGrhPNmd3B6MC0yF8AAIUAAOIAg0Imre3m-_32NMwBA","net.maunium.telegram.sticker":{"pack":{"id":"unimplemented","short_name":"AlwaysSunny"},"id":"unimplemented","emoticons":["🍑"]}},{"body":"😎","url":"mxc://xethos.net/zLqAtWveHUxqbsctshIdsYjr","info":{"w":512,"h":512,"size":20518,"mimetype":"image/webp","thumbnail_url":"mxc://xethos.net/zLqAtWveHUxqbsctshIdsYjr","thumbnail_info":{"w":512,"h":512,"size":20518,"mimetype":"image/webp"}},"msgtype":"m.sticker","id":"tg_file_id_CAACAgEAAxUAAWT9uWjhmTTSnoioqDH8WPG0Oig3AAIWAAOIAg0IVqdUSw3nDjgwBA","net.maunium.telegram.sticker":{"pack":{"id":"unimplemented","short_name":"AlwaysSunny"},"id":"unimplemented","emoticons":["😎"]}},{"body":"🐱","url":"mxc://xethos.net/XWwzNNAQhCIfroPLJcEWdwnp","info":{"w":512,"h":512,"size":17586,"mimetype":"image/webp","thumbnail_url":"mxc://xethos.net/XWwzNNAQhCIfroPLJcEWdwnp","thumbnail_info":{"w":512,"h":512,"size":17586,"mimetype":"image/webp"}},"msgtype":"m.sticker","id":"tg_file_id_CAACAgEAAxUAAWT9uWhfDhiC1U3Abfm99P-toH4jAAIaAAOIAg0I9gxbkufizpEwBA","net.maunium.telegram.sticker":{"pack":{"id":"unimplemented","short_name":"AlwaysSunny"},"id":"unimplemented","emoticons":["🐱"]}},{"body":"🎅","url":"mxc://xethos.net/gWZGOdQyMLVRDGBmBcuBZONC","info":{"w":512,"h":512,"size":36562,"mimetype":"image/webp","thumbnail_url":"mxc://xethos.net/gWZGOdQyMLVRDGBmBcuBZONC","thumbnail_info":{"w":512,"h":512,"size":36562,"mimetype":"image/webp"}},"msgtype":"m.sticker","id":"tg_file_id_CAACAgEAAxUAAWT9uWjr07bdJzCuxpM34VeP4hZFAAIcAAOIAg0I17wezFcv96QwBA","net.maunium.telegram.sticker":{"pack":{"id":"unimplemented","short_name":"AlwaysSunny"},"id":"unimplemented","emoticons":["🎅"]}},{"body":"🎄","url":"mxc://xethos.net/aLJzAWnlFETXpeCYVJbSVJaR","info":{"w":512,"h":512,"size":25684,"mimetype":"image/webp","thumbnail_url":"mxc://xethos.net/aLJzAWnlFETXpeCYVJbSVJaR","thumbnail_info":{"w":512,"h":512,"size":25684,"mimetype":"image/webp"}},"msgtype":"m.sticker","id":"tg_file_id_CAACAgEAAxUAAWT9uWhlSw6qBoQKpvVVa0SaxoguAAIeAAOIAg0IIegluHfeG9IwBA","net.maunium.telegram.sticker":{"pack":{"id":"unimplemented","short_name":"AlwaysSunny"},"id":"unimplemented","emoticons":["🎄"]}},{"body":"👄","url":"mxc://xethos.net/ACLSUGxXnTqfHxlYfncSvlGl","info":{"w":512,"h":512,"size":63600,"mimetype":"image/webp","thumbnail_url":"mxc://xethos.net/ACLSUGxXnTqfHxlYfncSvlGl","thumbnail_info":{"w":512,"h":512,"size":63600,"mimetype":"image/webp"}},"msgtype":"m.sticker","id":"tg_file_id_CAACAgEAAxUAAWT9uWjWCzUav1RM84G-pQ_sJxgsAAIgAAOIAg0IQy0usT2Y504wBA","net.maunium.telegram.sticker":{"pack":{"id":"unimplemented","short_name":"AlwaysSunny"},"id":"unimplemented","emoticons":["👄"]}},{"body":"😢","url":"mxc://xethos.net/uPjRGSbkRHBghhgcJMWcXmQo","info":{"w":512,"h":512,"size":25428,"mimetype":"image/webp","thumbnail_url":"mxc://xethos.net/uPjRGSbkRHBghhgcJMWcXmQo","thumbnail_info":{"w":512,"h":512,"size":25428,"mimetype":"image/webp"}},"msgtype":"m.sticker","id":"tg_file_id_CAACAgEAAxUAAWT9uWiP4GHtlaatBKu2_Y1Rq8pCAAIiAAOIAg0IJbVza0Si7IswBA","net.maunium.telegram.sticker":{"pack":{"id":"unimplemented","short_name":"AlwaysSunny"},"id":"unimplemented","emoticons":["😢"]}},{"body":"😀","url":"mxc://xethos.net/hNKyNJNlWBeGBFqnOtCGvBzD","info":{"w":512,"h":512,"size":26214,"mimetype":"image/webp","thumbnail_url":"mxc://xethos.net/hNKyNJNlWBeGBFqnOtCGvBzD","thumbnail_info":{"w":512,"h":512,"size":26214,"mimetype":"image/webp"}},"msgtype":"m.sticker","id":"tg_file_id_CAACAgEAAxUAAWT9uWip9oqSgrTMKA1QWmiI0lndAAIkAAOIAg0IbjER-0kb0JcwBA","net.maunium.telegram.sticker":{"pack":{"id":"unimplemented","short_name":"AlwaysSunny"},"id":"unimplemented","emoticons":["😀"]}},{"body":"😕","url":"mxc://xethos.net/kXPAOtYriivjKatCwTfHUHmE","info":{"w":512,"h":512,"size":39866,"mimetype":"image/webp","thumbnail_url":"mxc://xethos.net/kXPAOtYriivjKatCwTfHUHmE","thumbnail_info":{"w":512,"h":512,"size":39866,"mimetype":"image/webp"}},"msgtype":"m.sticker","id":"tg_file_id_CAACAgEAAxUAAWT9uWiCY-V_o02zrmZwd1qj30MLAAImAAOIAg0IVkQbBeHTMQwwBA","net.maunium.telegram.sticker":{"pack":{"id":"unimplemented","short_name":"AlwaysSunny"},"id":"unimplemented","emoticons":["😕"]}},{"body":"👽","url":"mxc://xethos.net/EkvoITzmpoAqDyrCJiAxlLnw","info":{"w":512,"h":512,"size":35034,"mimetype":"image/webp","thumbnail_url":"mxc://xethos.net/EkvoITzmpoAqDyrCJiAxlLnw","thumbnail_info":{"w":512,"h":512,"size":35034,"mimetype":"image/webp"}},"msgtype":"m.sticker","id":"tg_file_id_CAACAgEAAxUAAWT9uWidRW4sEdb9cdJguFV2zfNXAAIoAAOIAg0IPGwOEdMlCoQwBA","net.maunium.telegram.sticker":{"pack":{"id":"unimplemented","short_name":"AlwaysSunny"},"id":"unimplemented","emoticons":["👽"]}},{"body":"🌞","url":"mxc://xethos.net/UvIjgPpcFpYBgbLtaMjiNsnK","info":{"w":512,"h":512,"size":36920,"mimetype":"image/webp","thumbnail_url":"mxc://xethos.net/UvIjgPpcFpYBgbLtaMjiNsnK","thumbnail_info":{"w":512,"h":512,"size":36920,"mimetype":"image/webp"}},"msgtype":"m.sticker","id":"tg_file_id_CAACAgEAAxUAAWT9uWg2A4cmCtoXtMiJLV1t45T-AAIqAAOIAg0IsybaIsdrBBMwBA","net.maunium.telegram.sticker":{"pack":{"id":"unimplemented","short_name":"AlwaysSunny"},"id":"unimplemented","emoticons":["🌞"]}},{"body":"😁","url":"mxc://xethos.net/CnBbaRkYZZwFtfkjDWnCVaAt","info":{"w":512,"h":512,"size":34022,"mimetype":"image/webp","thumbnail_url":"mxc://xethos.net/CnBbaRkYZZwFtfkjDWnCVaAt","thumbnail_info":{"w":512,"h":512,"size":34022,"mimetype":"image/webp"}},"msgtype":"m.sticker","id":"tg_file_id_CAACAgEAAxUAAWT9uWgpuv0-iCeZdazvotPaJhfcAAIsAAOIAg0IkI-ZChhREcgwBA","net.maunium.telegram.sticker":{"pack":{"id":"unimplemented","short_name":"AlwaysSunny"},"id":"unimplemented","emoticons":["😁"]}},{"body":"😍","url":"mxc://xethos.net/tfycKyVAQCcHHBoYrRjspZKu","info":{"w":512,"h":512,"size":27624,"mimetype":"image/webp","thumbnail_url":"mxc://xethos.net/tfycKyVAQCcHHBoYrRjspZKu","thumbnail_info":{"w":512,"h":512,"size":27624,"mimetype":"image/webp"}},"msgtype":"m.sticker","id":"tg_file_id_CAACAgEAAxUAAWT9uWj34YDXTne6mv_Hj2q5Obc8AAIwAAOIAg0IgM9o3r9JDgEwBA","net.maunium.telegram.sticker":{"pack":{"id":"unimplemented","short_name":"AlwaysSunny"},"id":"unimplemented","emoticons":["😍"]}},{"body":"🍻","url":"mxc://xethos.net/nVRkfmtQZQgCicBrWpbEyDXD","info":{"w":512,"h":512,"size":42794,"mimetype":"image/webp","thumbnail_url":"mxc://xethos.net/nVRkfmtQZQgCicBrWpbEyDXD","thumbnail_info":{"w":512,"h":512,"size":42794,"mimetype":"image/webp"}},"msgtype":"m.sticker","id":"tg_file_id_CAACAgEAAxUAAWT9uWjmtykjYN4ShMbwHFcqohxfAAIyAAOIAg0IXxX7sVPTAcEwBA","net.maunium.telegram.sticker":{"pack":{"id":"unimplemented","short_name":"AlwaysSunny"},"id":"unimplemented","emoticons":["🍻"]}},{"body":"😊","url":"mxc://xethos.net/ZzelbsYnNdlmVGPfBGMVeCdU","info":{"w":512,"h":512,"size":37468,"mimetype":"image/webp","thumbnail_url":"mxc://xethos.net/ZzelbsYnNdlmVGPfBGMVeCdU","thumbnail_info":{"w":512,"h":512,"size":37468,"mimetype":"image/webp"}},"msgtype":"m.sticker","id":"tg_file_id_CAACAgEAAxUAAWT9uWjJYm9Xdd5eHqkOB9MHRo4hAAI1AAOIAg0I901h2hL8QiUwBA","net.maunium.telegram.sticker":{"pack":{"id":"unimplemented","short_name":"AlwaysSunny"},"id":"unimplemented","emoticons":["😊"]}},{"body":"😡","url":"mxc://xethos.net/rmibxzAtmNylUGWZOxmowFYX","info":{"w":512,"h":512,"size":30092,"mimetype":"image/webp","thumbnail_url":"mxc://xethos.net/rmibxzAtmNylUGWZOxmowFYX","thumbnail_info":{"w":512,"h":512,"size":30092,"mimetype":"image/webp"}},"msgtype":"m.sticker","id":"tg_file_id_CAACAgEAAxUAAWT9uWgW2V4qQ6-4gpnMC8lQMeaTAAI3AAOIAg0I9WpDRK4uctEwBA","net.maunium.telegram.sticker":{"pack":{"id":"unimplemented","short_name":"AlwaysSunny"},"id":"unimplemented","emoticons":["😡"]}},{"body":"👶","url":"mxc://xethos.net/MPJsNCfUMpbPWYFTccFNBHML","info":{"w":512,"h":512,"size":17446,"mimetype":"image/webp","thumbnail_url":"mxc://xethos.net/MPJsNCfUMpbPWYFTccFNBHML","thumbnail_info":{"w":512,"h":512,"size":17446,"mimetype":"image/webp"}},"msgtype":"m.sticker","id":"tg_file_id_CAACAgEAAxUAAWT9uWjUAmxvLSCxXVjLRuC8-n9DAAI5AAOIAg0I78tpYopuqMswBA","net.maunium.telegram.sticker":{"pack":{"id":"unimplemented","short_name":"AlwaysSunny"},"id":"unimplemented","emoticons":["👶"]}},{"body":"💪","url":"mxc://xethos.net/wLYbDzFKJdjWEpXKsIRCuBgg","info":{"w":512,"h":512,"size":34906,"mimetype":"image/webp","thumbnail_url":"mxc://xethos.net/wLYbDzFKJdjWEpXKsIRCuBgg","thumbnail_info":{"w":512,"h":512,"size":34906,"mimetype":"image/webp"}},"msgtype":"m.sticker","id":"tg_file_id_CAACAgEAAxUAAWT9uWgcjoRSldHUK_Z-hMDC3tljAAI7AAOIAg0IcoJBkJD0tbgwBA","net.maunium.telegram.sticker":{"pack":{"id":"unimplemented","short_name":"AlwaysSunny"},"id":"unimplemented","emoticons":["💪"]}},{"body":"🐱","url":"mxc://xethos.net/UaNGWsrNPrNximLjficRLetK","info":{"w":512,"h":512,"size":48218,"mimetype":"image/webp","thumbnail_url":"mxc://xethos.net/UaNGWsrNPrNximLjficRLetK","thumbnail_info":{"w":512,"h":512,"size":48218,"mimetype":"image/webp"}},"msgtype":"m.sticker","id":"tg_file_id_CAACAgEAAxUAAWT9uWggBG9J3uOuZ8G6-J5fuPo-AAJDAAOIAg0IHyDiMJOuL1UwBA","net.maunium.telegram.sticker":{"pack":{"id":"unimplemented","short_name":"AlwaysSunny"},"id":"unimplemented","emoticons":["🐱"]}},{"body":"🍩","url":"mxc://xethos.net/ONIgCdlxumgagoIGNBDiwuhJ","info":{"w":512,"h":512,"size":25958,"mimetype":"image/webp","thumbnail_url":"mxc://xethos.net/ONIgCdlxumgagoIGNBDiwuhJ","thumbnail_info":{"w":512,"h":512,"size":25958,"mimetype":"image/webp"}},"msgtype":"m.sticker","id":"tg_file_id_CAACAgEAAxUAAWT9uWgfXNJJne45RAVYUAH4r9QMAAJHAAOIAg0IveHBlQ0G2BcwBA","net.maunium.telegram.sticker":{"pack":{"id":"unimplemented","short_name":"AlwaysSunny"},"id":"unimplemented","emoticons":["🍩"]}},{"body":"🍌","url":"mxc://xethos.net/RGsFOQhabSluhXuxsummzmQX","info":{"w":512,"h":512,"size":22158,"mimetype":"image/webp","thumbnail_url":"mxc://xethos.net/RGsFOQhabSluhXuxsummzmQX","thumbnail_info":{"w":512,"h":512,"size":22158,"mimetype":"image/webp"}},"msgtype":"m.sticker","id":"tg_file_id_CAACAgEAAxUAAWT9uWj9mxyfj2XwId8R6gsYgIV_AAJJAAOIAg0II8bLvrMS05MwBA","net.maunium.telegram.sticker":{"pack":{"id":"unimplemented","short_name":"AlwaysSunny"},"id":"unimplemented","emoticons":["🍌"]}},{"body":"😬","url":"mxc://xethos.net/PWEinbXCQSuWuEyjoUsDEfVE","info":{"w":512,"h":512,"size":31044,"mimetype":"image/webp","thumbnail_url":"mxc://xethos.net/PWEinbXCQSuWuEyjoUsDEfVE","thumbnail_info":{"w":512,"h":512,"size":31044,"mimetype":"image/webp"}},"msgtype":"m.sticker","id":"tg_file_id_CAACAgEAAxUAAWT9uWgxpIPD-6WqcfCqJ_476n2QAAJMAAOIAg0I2QWFrWPjEKswBA","net.maunium.telegram.sticker":{"pack":{"id":"unimplemented","short_name":"AlwaysSunny"},"id":"unimplemented","emoticons":["😬"]}}]}